{
    "strings" : {
        "Age-yo": {
            "en": "y.o.",
            "ru": "лет",
            "kz": "жас"
        },
        "carouselContinueButtonText": {
            "en": "Next",
            "ru": "Далее",
            "kz": "Келесі"
        },
        "carouselEndButtonText": {
            "en": "Let's start!",
            "ru": "Начнем!",
            "kz": "Әрі қарай"
        },
        "carouselItem-1": {
            "en": "Movies, TV series, sitcoms, animation projects, TV programs and reality shows, anime and much more",
            "ru": "Фильмы, сериалы, ситкомы, анимационные проекты, телепрограммы и реалити-шоу, аниме и многое другое",
            "kz": "Фильмдер, телехикаялар, ситкомдар, анимациялық жобалар, телебағдарламалар мен реалити-шоулар, аниме және тағы басқалары"
        },
        "carouselItem-2": {
            "en": "Look from any device\nWatch your favorite movie from your phone, tablet, laptop without additional payment",
            "ru": "Смотрите с любого устройства\nСмотрите свой любимый фильм со своего телефона, планшета, ноутбука без дополнительной оплаты",
            "kz": "Кез келген құрылғыдан қара \nСүйікті фильміңді  қосымша төлемсіз телефоннан, планшеттен, ноутбуктан қара"
        },
        "carouselItem-3": {
            "en": "Registration is easy. Register now and get the movie you want",
            "ru": "Зарегистрироваться очень просто. Зарегистрируйтесь прямо сейчас и получите желаемый фильм",
            "kz": "Тіркелу оңай. Қазір тіркел де қалаған фильміңе қол жеткіз"
        },
        "carouselSkipButton": {
            "en": "Skip",
            "ru": "Пропустить",
            "kz": "Өткізу"
        },
        "carouselWelcomeText": {
            "en": "Welcome to ÖZINŞE!",
            "ru": "Добро пожаловать в ÖZINŞE!",
            "kz": "ÖZINŞE-ге қош келдің!"
        },
        "ChangePassword-NewPassword": {
            "en": "New password",
            "ru": "Новый пароль",
            "kz": "Жаңа пароль"
        },
        "ChangePassword-RepeatPassword": {
            "en": "Repeat new password",
            "ru": "Повторите новый пароль",
            "kz": "Жаңа құпия сөзді қайталаңыз"
        },
        "ChangeTheme-Warning": {
            "en": "To successfully change the theme of the application, please restart the application",
            "ru": "Для успешной смены темы приложения, пожалуйста, перезагрузите приложение",
            "kz": "Қолданба тақырыбын сәтті өзгерту үшін қолданбаны қайта жүктеңіз"
        },
        "ContentCategories-Anime": {
            "en": "Anime",
            "ru": "Аниме",
            "kz": "Аниме"
        },
        "ContentCategories-Cartoons": {
            "en": "Cartoons",
            "ru": "Мультфильмы",
            "kz": "Мультсериал"
        },
        "ContentCategories-CartoonSeries": {
            "en": "CartoonSeries",
            "ru": "Мультсериалы",
            "kz": "Мультфильм"
        },
        "ContentCategories-Documentary": {
            "en": "Documentary movies",
            "ru": "Документальные фильмы",
            "kz": "Деректі фильм"
        },
        "ContentCategories-FeatureMovies": {
            "en": "Feature Movies",
            "ru": "Художественный фильмы",
            "kz": "Көркем фильм"
        },
        "ContentCategories-Foreign": {
            "en": "Foreign films",
            "ru": "Зарубежные фильмы",
            "kz": "Шетел фильмдері"
        },
        "ContentCategories-Music": {
            "en": "Music",
            "ru": "Музыка",
            "kz": "Музыка"
        },
        "ContentCategories-Series": {
            "en": "Series",
            "ru": "Сериалы",
            "kz": "Телехикая"
        },
        "ContentCategories-Sitkom": {
            "en": "Sitkom",
            "ru": "Ситком",
            "kz": "Ситком"
        },
        "ContentCategories-TVShow": {
            "en": "TV program and reality show",
            "ru": "ТВ-программы и реалити-шоу",
            "kz": "Тв-бағдарлама және реалити-шоу"
        },
        "Favorites-Title": {
            "en": "Favorites",
            "ru": "Избранное",
            "kz": "Таңдаулылар"
        },
        "GalleryList-TVProgram": {
            "en": "TV program and reality show",
            "ru": "ТВ-программы и реалити-шоу",
            "kz": "Тв-бағдарлама және реалити-шоу"
        },
        "General-Categories": {
            "en": "Categories",
            "ru": "Категории",
            "kz": "Санаттар"
        },
        "General-Edit": {
            "en": "Edit",
            "ru": "Изменить",
            "kz": "Өңдеу"
        },
        "General-FunctionUnavailableError": {
            "en": "We are sorry! This options is not working now",
            "ru": "Приносим свои извинения! Эта опция сейчас не работает",
            "kz": "Кешіріңіз! Бұл опциялар қазір жұмыс істемейді"
        },
        "General-IncorrectFormat": {
            "en": "Incorrect format for login or password! Pleas, check it and try again",
            "ru": "Неверный формат ввода логина или пароля! Пожалуйста, проверьте его и повторите попытку",
            "kz": "Логин немесе пароль үшін қате формат! Өтінемін, оны тексеріп, қайталап көріңіз"
        },
        "General-UnknownError": {
            "en": "An unknown error has occurred! Please try again later!",
            "ru": "Произошла неизвестная ошибка! Пожалуйста, попробуйте позже!",
            "kz": "Белгісіз қате болды! Өтінемін, кейінірек көріңіз!"
        },
        "Genres-Adventure": {
            "en": "Adventure",
            "ru": "Приключения",
            "kz": "Шытырман оқиғалы"
        },
        "Genres-Comedy": {
            "en": "Comedy",
            "ru": "Комении",
            "kz": "Комедиялар"
        },
        "Genres-Entertainment": {
            "en": "Entertainment",
            "ru": "Развлечения",
            "kz": "Ойын-сауық"
        },
        "Genres-Family": {
            "en": "Family",
            "ru": "Семья",
            "kz": "Отбасымен көретіндер"
        },
        "Genres-Fantasy": {
            "en": "Fantasy",
            "ru": "Фэнтези",
            "kz": "Ғылыми фантастика және фэнтези"
        },
        "Genres-Musically": {
            "en": "Musically",
            "ru": "Музыка",
            "kz": "Музыкалық"
        },
        "Genres-Science": {
            "en": "Science",
            "ru": "Научные",
            "kz": "Ғылыми-танымдық"
        },
        "Genres-Short": {
            "en": "Short",
            "ru": "Короткометражные",
            "kz": "Қысқаметрлі"
        },
        "Genres-Sport": {
            "en": "Sport",
            "ru": "Спорт",
            "kz": "Спорттық"
        },
        "KeepWatching-KeepWatching": {
            "en": "Keep watching",
            "ru": "Продолжить просмотр",
            "kz": "Көруді жалғастырыңыз"
        },
        "Languages-Cancel": {
            "en": "Cancel",
            "ru": "Отменить",
            "kz": "Болдырмау"
        },
        "Languages-Restart": {
            "en": "Restart",
            "ru": "Перезагрузить",
            "kz": "Қайта қосу"
        },
        "Languages-Warning": {
            "en": "Warning",
            "ru": "Внимание",
            "kz": "Ескерту"
        },
        "Lanuages-WarningDescription": {
            "en": "Please restart your app to change language completely",
            "ru": "Пожалуйста, перезапустите ваше приложение, чтобы полностью сменить язык",
            "kz": "Тілді толығымен өзгерту үшін қолданбаны қайта іске қосыңыз"
        },
        "LeaveAccount-Confirmation": {
            "en": "Do you really want to log out of your account?",
            "ru": "Вы действительно хотите выйти из аккаунта?",
            "kz": "Сіз шынымен есептік жазбаңыздан шыққыңыз келе ме?"
        },
        "LeaveAccount-No": {
            "en": "No",
            "ru": "Нет",
            "kz": "Жоқ"
        },
        "LeaveAccount-Yes": {
            "en": "Yes. leave",
            "ru": "Да, выйти",
            "kz": "Иә, шығу"
        },
        "Login-IncorrectLoginOrPassword": {
            "en": "Incorrect login or password",
            "ru": "Неверный логин или пароль",
            "kz": "Логин немесе құпия сөз дұрыс емес"
        },
        "Movie-Director": {
            "en": "Director",
            "ru": "Режисер",
            "kz": "Режиссер"
        },
        "Movie-Hide": {
            "en": "Hide",
            "ru": "Скрыть",
            "kz": "Жасыру"
        },
        "Movie-More": {
            "en": "More",
            "ru": "Больше",
            "kz": "Толығырақ"
        },
        "Movie-Producer": {
            "en": "Producer",
            "ru": "Продюсер",
            "kz": "Продюсер"
        },
        "General-Save": {
            "en": "Save",
            "ru": "Сохранить",
            "kz": "Сақтау"
        },
        "Movie-Screenshots": {
            "en": "Screenshots",
            "ru": "Скриншоты",
            "kz": "Скриншоттар"
        },
        "Movie-Sections": {
            "en": "Sections",
            "ru": "Секции",
            "kz": "Бөлімдер"
        },
        "Movie-Share": {
            "en": "Share",
            "ru": "Поделиться",
            "kz": "Бөлісу"
        },
        "Movie-SimilarShows": {
            "en": "Similar TV series",
            "ru": "Похожие сериалы",
            "kz": "Ұқсас телехикаялар"
        },
        "Movie-Watch": {
            "en": "Watch",
            "ru": "Посмотреть",
            "kz": "Қарау"
        },
        "MovieInfo-FromItsCategory": {
            "en": "From the same category",
            "ru": "Из этой же категории",
            "kz": "Сол санаттан"
        },
        "MovieInfo-Trending": {
            "en": "Trending ones",
            "ru": "В тренде",
            "kz": "Трендтер"
        },
        "PersonalData-birhdayDate": {
            "en": "Birthday date",
            "ru": "Дата рождения",
            "kz": "Туған күні"
        },
        "PersonalData-name": {
            "en": "Name",
            "ru": "Имя",
            "kz": "Сіздің атыңыз"
        },
        "PersonalData-NoData": {
            "en": "Empty",
            "ru": "Пусто",
            "kz": "Бос"
        },
        "PersonalData-phoneNumber": {
            "en": "Phone number",
            "ru": "Номер телефона",
            "kz": "Телефон нөмірі"
        },
        "Profile-ChangePassword": {
            "en": "Change password",
            "ru": "Изменить пароль",
            "kz": "Құпия сөзді өзгерту"
        },
        "Profile-DarkMode": {
            "en": "Dark mode",
            "ru": "Ночной режим",
            "kz": "Қараңғы режим"
        },
        "Profile-Language": {
            "en": "Language",
            "ru": "Язык",
            "kz": "Тіл"
        },
        "Profile-Leave": {
            "en": "Leave",
            "ru": "Выйти",
            "kz": "Шығу"
        },
        "Profile-MyProfile": {
            "en": "My profile",
            "ru": "Мой профиль",
            "kz": "Менің профилім"
        },
        "Profile-Notifications": {
            "en": "Notifications",
            "ru": "Уведомления",
            "kz": "Хабарламалар"
        },
        "Profile-PersonalData": {
            "en": "Personal data",
            "ru": "Персональные данные",
            "kz": "Жеке деректер"
        },
        "Profile-Profile": {
            "en": "Profile",
            "ru": "Профиль",
            "kz": "Профиль"
        },
        "Profile-TermsOfUse": {
            "en": "Terms of Use",
            "ru": "Условия использования",
            "kz": "Ережелер мен шарттар"
        },
        "Search-NoResults": {
            "en": "Your search returned no results",
            "ru": "Ваш поиск не дал никаких результатов",
            "kz": "Сіздің іздеуіңіз нәтиже бермеді"
        },
        "Search-Search": {
            "en": "Search",
            "ru": "Поиск",
            "kz": "Іздеу"
        },
        "Seasons-episode": {
            "en": "episode",
            "ru": "эпизод",
            "kz": "эпизод"
        },
        "Seasons-Seasons": {
            "en": "season",
            "ru": "сезон",
            "kz": "маусым"
        },
        "Series-episode": {
            "en": "episode",
            "ru": "серия",
            "kz": "серия"
        },
        "SignIn-AppleID": {
            "en": "Sign up with your Apple ID",
            "ru": "Войти с Apple ID",
            "kz": "Apple ID-мен тіркеліңіз"
        },
        "SignIn-Description": {
            "en": "Log in into your account",
            "ru": "Войдите в ваш аккаунт",
            "kz": "Аккаунтқа кіріңіз"
        },
        "SignIn-EmailIsEmpty": {
            "en": "Email or password cannot be empty",
            "ru": "Адрес электронной почты или пароль не могут быть пустыми",
            "kz": "Электрондық пошта немесе құпия сөз бос болуы мүмкін емес"
        },
        "SignIn-ForgotPassword": {
            "en": "Forgot your password?",
            "ru": "Забыли пароль?",
            "kz": "Құпия сөзді ұмыттыңыз ба?"
        },
        "SignIn-Google": {
            "en": "Sign up with your Google",
            "ru": "Войти с Google",
            "kz": "Google-мен тіркеліңіз"
        },
        "SignIn-HaveNoAccount": {
            "en": "Have no account?",
            "ru": "Нет аккаунта?",
            "kz": "Аккаунтыныз жоқ па? "
        },
        "SignIn-Hello": {
            "en": "Hello",
            "ru": "Привет!",
            "kz": "Сәлем"
        },
        "SignIn-Join": {
            "en": "Join",
            "ru": "Войти",
            "kz": "Кіру"
        },
        "SignIn-or": {
            "en": "Or try it",
            "ru": "Или",
            "kz": "Немесе"
        },
        "SignIn-Password": {
            "en": "Password",
            "ru": "Пароль",
            "kz": "Құпия сөз"
        },
        "SignIn-SignUp": {
            "en": "Sign Up!",
            "ru": "Зарегистрироваться!",
            "kz": "Тіркелу"
        },
        "SignIn-WrongFormat": {
            "en": "Wrong format",
            "ru": "Неверный формат",
            "kz": "Қате формат"
        },
        "SignIn-YourEmail": {
            "en": "Your email",
            "ru": "Ваш email",
            "kz": "Сіздің email"
        },
        "SignIn-YourPassword": {
            "en": "Your password",
            "ru": "Ваш пароль",
            "kz": "Сіздің құпия сөзіңіз"
        },
        "SignUp-Description": {
            "en": "Fill in the data",
            "ru": "Заполните форму",
            "kz": "Деректерді толтырыңыз"
        },
        "SignUp-DoUHaveAnAccount?": {
            "en": "Already have an account?",
            "ru": "Уже есть аккаунт?",
            "kz": "Сізде аккаунт бар ма?"
        },
        "SignUp-Login": {
            "en": "Login",
            "ru": "Войти",
            "kz": "Кіру"
        },
        "SignUp-PasswordAgain": {
            "en": "Repeat the password",
            "ru": "Повторите пароль",
            "kz": "Құпия сөзді қайталаңыз"
        },
        "SignUp-PasswordsAreDifferent": {
            "en": "Passwords are not similar",
            "ru": "Пароли не совпадают между собой",
            "kz": "Парольдер ұқсас емес"
        },
        "SignUp-SignUp": {
            "en": "Sign Up",
            "ru": "Зарегистрироваться",
            "kz": "Тіркелу"
        },
        "PersonalData-Title": {
            "en": "Personal Data",
            "ru": "Персональные данные",
            "kz": "Дербес деректер"
        },
        "Favorites-ErrorTitle": {
            "en": "🙊 Oops... there is nothing!",
            "ru": "🙊 Ой, здесь пусто!",
            "kz": "🙊 Ой-бай! Осында iштене жок"
        },
        "Favorites-ErrorBody": {
            "en": "But you can fill it by adding any movie to favorites!",
            "ru": "Но вы можете заполнить его, добавив любой фильм в избранное!",
            "kz": "Бірақ сіз оны кез-келген фильмді таңдаулыларға қосу арқылы толтыра аласыз!"
        },
        "Favorites-LookButton": {
            "en": "Look out!",
            "ru": "Поехали!",
            "kz": "Сақтан!"
        },
        "PoorNetwork-Title": {
            "en": "Connect to the Internet",
            "ru": "Подключитесь к Интернету",
            "kz": "Интернетке қосылыңыз"
        },
        "PoorNetwork-Body": {
            "en": "You're offline. Check your connection",
            "ru": "Ваше устройство не имеет подлкючения к интернету",
            "kz": "Сіздің құрылғыңызда интернет байланысы жоқ"
        },
        "PoorNetwork-TryAgain": {
            "en": "Tap ro retry",
            "ru": "Повторить попытку",
            "kz": "Қайталап көріңіз"
        },
        "PullToRefresh": {
            "en": "Pull to refresh",
            "ru": "Потяните для обновления",
            "kz": "Сергіту үшін тартыңыз"
        }
    }
}
